LICENSE
gitea/__init__.py
gitea/apiobject.py
gitea/baseapiobject.py
gitea/exceptions.py
gitea/gitea.py
gipea-0.11.2.dist-info/LICENSE
gipea-0.11.2.dist-info/METADATA
gipea-0.11.2.dist-info/WHEEL
gipea-0.11.2.dist-info/RECORD
