Metadata-Version: 2.1
Name: gipea
Version: 0.11.2
Summary: A gitea python API wrapper
Home-page: https://github.com/AthAshino/gipea
License: MIT
Keywords: gitea,api
Author: Ashino
Requires-Python: >=3.10,<4.0
Classifier: Development Status :: 4 - Beta
Classifier: Environment :: Console
Classifier: Intended Audience :: Developers
Classifier: License :: OSI Approved :: MIT License
Classifier: Operating System :: OS Independent
Classifier: Programming Language :: Python :: 3
Classifier: Programming Language :: Python :: 3.10
Classifier: Programming Language :: Python :: 3.11
Classifier: Programming Language :: Python :: 3.12
Classifier: Topic :: Software Development :: Libraries :: Python Modules
Classifier: Topic :: Software Development :: Quality Assurance
Requires-Dist: frozendict (>=2.3.8)
Requires-Dist: requests (>=2.31.0)
Project-URL: Repository, https://github.com/AthAshino/gipea
